{"version":1,"resource":"file:///home/sdhz/Desktop/Purwadhika/blog-next14/apps/web/src/components/ui/PreviewImage.tsx","entries":[{"id":"jTVJ.tsx","timestamp":1715071438787},{"id":"zwwG.tsx","timestamp":1715071484362},{"id":"BQ0K.tsx","timestamp":1715071539510},{"id":"Yog4.tsx","timestamp":1715071626534},{"id":"neND.tsx","timestamp":1715071642085},{"id":"wtM2.tsx","timestamp":1715071656813},{"id":"E7gu.tsx","timestamp":1715071681833},{"id":"iD9k.tsx","timestamp":1715071806217},{"id":"FPbx.tsx","timestamp":1715071819492},{"id":"BrOL.tsx","timestamp":1715071910788},{"id":"dr58.tsx","timestamp":1715071983676},{"id":"2cvO.tsx","timestamp":1715072002459},{"id":"z6EZ.tsx","timestamp":1715072033215},{"id":"QtEy.tsx","timestamp":1715072098335},{"id":"qO6w.tsx","timestamp":1715072134243},{"id":"4vbe.tsx","timestamp":1715072155871},{"id":"D1Yb.tsx","timestamp":1715072182338}]}